smplzgmodule2/__init__.py
smplzgmodule2/smplzgmodule.py
smplzgmodule2-0.0.5.dist-info/METADATA
smplzgmodule2-0.0.5.dist-info/WHEEL
smplzgmodule2-0.0.5.dist-info/top_level.txt
smplzgmodule2-0.0.5.dist-info/RECORD
