Metadata-Version: 2.1
Name: smplzgmodule2
Version: 0.0.5
Summary: My first Python package
Home-page: UNKNOWN
Author: Zach G
Author-email: <youremail@email.com>
License: UNKNOWN
Keywords: python,first package
Platform: UNKNOWN
Classifier: Development Status :: 3 - Alpha
Classifier: Intended Audience :: Education
Classifier: Programming Language :: Python :: 2
Classifier: Programming Language :: Python :: 3
Classifier: Operating System :: MacOS :: MacOS X
Classifier: Operating System :: Microsoft :: Windows
Requires-Dist: pandas
Requires-Dist: textblob
Requires-Dist: tweetpy
